builds/Dockerfile.doc
builds/nginx-default.conf
prismstudio/__init__.py
prismstudio/_common/__init__.py
prismstudio/_common/config.env
prismstudio/_common/config.py
prismstudio/_common/const.py
prismstudio/_common/mode.env
prismstudio/_core/__init__.py
prismstudio/_core/_fn.py
prismstudio/_core/ols.py
prismstudio/_core/_data/__init__.py
prismstudio/_core/_data/afl.py
prismstudio/_core/_data/company.py
prismstudio/_core/_data/economics.py
prismstudio/_core/_data/esg.py
prismstudio/_core/_data/estimate.py
prismstudio/_core/_data/event.py
prismstudio/_core/_data/financial.py
prismstudio/_core/_data/index.py
prismstudio/_core/_data/market.py
prismstudio/_core/_data/reference.py
prismstudio/_core/_data/securitymaster.py
prismstudio/_core/_data/starmine.py
prismstudio/_core/_data/transaction.py
prismstudio/_core/_model/__init__.py
prismstudio/_core/_model/riskmodel.py
prismstudio/_core/_model/tcmodel.py
prismstudio/_core/_req_builder/__init__.py
prismstudio/_core/_req_builder/_auth.py
prismstudio/_core/_req_builder/_dataquery.py
prismstudio/_core/_req_builder/_exportdata.py
prismstudio/_core/_req_builder/_gui.py
prismstudio/_core/_req_builder/_job.py
prismstudio/_core/_req_builder/_list.py
prismstudio/_core/_req_builder/_portfolio.py
prismstudio/_core/_req_builder/_securitymaster.py
prismstudio/_core/_req_builder/_taskquery.py
prismstudio/_core/_req_builder/_universe.py
prismstudio/_core/_req_builder/admin.py
prismstudio/_core/_req_builder/preference.py
prismstudio/_core/_task/__init__.py
prismstudio/_core/_task/backtest.py
prismstudio/_core/_task/data.py
prismstudio/_core/_task/screen.py
prismstudio/_prismcomponent/__init__.py
prismstudio/_prismcomponent/abstract_prismcomponent.py
prismstudio/_prismcomponent/prismcomponent.py
prismstudio/_utils/__init__.py
prismstudio/_utils/auth_utils.py
prismstudio/_utils/exceptions.py
prismstudio/_utils/loader.py
prismstudio/_utils/modes.py
prismstudio/_utils/prismcomponent_utils.py
prismstudio/_utils/req_builder_utils.py
prismstudio-1.7.6.dist-info/licenses/LICENSE.txt
prismstudio-1.7.6.dist-info/METADATA
prismstudio-1.7.6.dist-info/WHEEL
prismstudio-1.7.6.dist-info/top_level.txt
prismstudio-1.7.6.dist-info/RECORD
