Metadata-Version: 2.4
Name: prismstudio
Version: 1.7.6
Summary: PrismStudio by Prism39
Author-email: "Prism39 Inc." <info@prism39.com>
License: PrismStudio End User License Agreement
Classifier: Programming Language :: Python
Classifier: Programming Language :: Python :: 3
Classifier: Programming Language :: Python :: 3 :: Only
Classifier: Programming Language :: Python :: 3.10
Classifier: Programming Language :: Python :: 3.11
Classifier: Programming Language :: Python :: 3.12
Classifier: Programming Language :: Python :: 3.13
Requires-Python: >=3.8
License-File: LICENSE.txt
Requires-Dist: pandas
Requires-Dist: polars
Requires-Dist: pyarrow
Requires-Dist: tqdm
Requires-Dist: orjson
Requires-Dist: requests
Requires-Dist: ipywidgets
Requires-Dist: pydantic
Requires-Dist: pydantic-settings
Requires-Dist: sseclient-py
Dynamic: license-file
